caitk/__init__.py
caitk-0.0.7.dist-info/LICENSE.md
caitk-0.0.7.dist-info/METADATA
caitk-0.0.7.dist-info/WHEEL
caitk-0.0.7.dist-info/top_level.txt
caitk-0.0.7.dist-info/zip-safe
caitk-0.0.7.dist-info/RECORD
