Metadata-Version: 2.1
Name: caitk
Version: 0.0.7
Summary: Caitum Artificial Intelligence Toolkit
Home-page: https://github.com/caitum/caitk
Author: Caitum Technologies
Author-email: devel@caitum.com
License: GPL-3.0-only
Project-URL: Issues, https://github.com/caitum/caitk/issues
Keywords: caitum artificial-intelligence
Platform: UNKNOWN
Classifier: Development Status :: 1 - Planning
Classifier: License :: OSI Approved :: GNU General Public License v3 (GPLv3)
Classifier: Intended Audience :: Developers
Classifier: Intended Audience :: Science/Research
Classifier: Programming Language :: Python :: 3.7
Classifier: Topic :: Scientific/Engineering :: Artificial Intelligence
Classifier: Topic :: Scientific/Engineering :: Mathematics
Classifier: Topic :: Software Development :: Libraries :: Python Modules
